rasode_mei_kaun_tha/__init__.py
rasode_mei_kaun_tha/disp.jpg
rasode_mei_kaun_tha/kaun_tha.py
rasode_mei_kaun_tha-0.1.3.dist-info/METADATA
rasode_mei_kaun_tha-0.1.3.dist-info/WHEEL
rasode_mei_kaun_tha-0.1.3.dist-info/top_level.txt
rasode_mei_kaun_tha-0.1.3.dist-info/RECORD
