Metadata-Version: 2.1
Name: rasode-mei-kaun-tha
Version: 0.1.3
Summary: the mystery unveiled
Home-page: https://github.com/imZain448/dummy_pypi_package
Author: imzain448
Author-email: ahmadzain.448@gmail.com
License: UNKNOWN
Platform: UNKNOWN
Classifier: Programming Language :: Python :: 3
Classifier: License :: OSI Approved :: MIT License
Classifier: Operating System :: OS Independent
Requires-Python: >=3.6
Requires-Dist: matplotlib
